py_flare_common/__init__.py
py_flare_common/_hexstr/__init__.py
py_flare_common/_hexstr/hexstr.py
py_flare_common/b58/__init__.py
py_flare_common/b58/flare_b58.py
py_flare_common/fdc/__init__.py
py_flare_common/fdc/attestation_source.py
py_flare_common/fdc/attestation_type.py
py_flare_common/fsp/epoch/__init__.py
py_flare_common/fsp/epoch/epoch.py
py_flare_common/fsp/epoch/factory.py
py_flare_common/fsp/epoch/timing/__init__.py
py_flare_common/fsp/epoch/timing/config.py
py_flare_common/fsp/epoch/timing/coston/__init__.py
py_flare_common/fsp/epoch/timing/coston/epoch.py
py_flare_common/fsp/epoch/timing/coston2/__init__.py
py_flare_common/fsp/epoch/timing/coston2/epoch.py
py_flare_common/fsp/epoch/timing/flare/__init__.py
py_flare_common/fsp/epoch/timing/flare/epoch.py
py_flare_common/fsp/epoch/timing/songbird/__init__.py
py_flare_common/fsp/epoch/timing/songbird/epoch.py
py_flare_common/fsp/messaging/__init__.py
py_flare_common/fsp/messaging/byte_parser.py
py_flare_common/fsp/messaging/parse.py
py_flare_common/fsp/messaging/types.py
py_flare_common/ftso/__init__.py
py_flare_common/ftso/commit.py
py_flare_common/ftso/fast_updates.py
py_flare_common/ftso/feed.py
py_flare_common/ftso/median.py
py_flare_common/merkle/__init__.py
py_flare_common/merkle/tree.py
py_flare_common/smart_accounts/__init__.py
py_flare_common/smart_accounts/encoder/__init__.py
py_flare_common/smart_accounts/encoder/decoder.py
py_flare_common/smart_accounts/encoder/exceptions.py
py_flare_common/smart_accounts/encoder/instructions.py
py_flare_common/smart_accounts/encoder/validators.py
py_flare_common-0.1.7.dist-info/METADATA
py_flare_common-0.1.7.dist-info/WHEEL
py_flare_common-0.1.7.dist-info/top_level.txt
py_flare_common-0.1.7.dist-info/RECORD
